LICENSE
README.md
setup.py
scikit_duplo.egg-info/PKG-INFO
scikit_duplo.egg-info/SOURCES.txt
scikit_duplo.egg-info/dependency_links.txt
scikit_duplo.egg-info/requires.txt
scikit_duplo.egg-info/top_level.txt
skduplo/__init__.py
skduplo/meta/__init__.py
skduplo/meta/baseline_proportional_regressor.py
skduplo/meta/quantile_stack_multi_regressor.py
skduplo/meta/quantile_stack_regressor.py
skduplo/meta/regressor_stack.py
skduplo/preprocessing/__init__.py
skduplo/preprocessing/column_concatenator.py
skduplo/preprocessing/lookup_encoder.py
skduplo/preprocessing/two_column_ratio_diff.py